passwordCracker/__init__.py
passwordCracker-2.0.dist-info/LICENSE
passwordCracker-2.0.dist-info/METADATA
passwordCracker-2.0.dist-info/WHEEL
passwordCracker-2.0.dist-info/top_level.txt
passwordCracker-2.0.dist-info/RECORD
