Metadata-Version: 2.1
Name: passwordCracker
Version: 2.0
Summary: A tool to perform a dictionary attack to OS hashes file.
Author: Cristina Galván
Author-email: cristina.galvan.prieto@hotmail.com
License: GNU GPLv3
Keywords: cybersecurity cracking dictionary attack passwords OS
Classifier: Development Status :: 5 - Production/Stable
Classifier: Intended Audience :: Developers
Classifier: Topic :: Security :: Cryptography
Classifier: License :: OSI Approved :: GNU General Public License v3 (GPLv3)
Classifier: Programming Language :: Python :: 3
Classifier: Operating System :: OS Independent
License-File: LICENSE
